<root>
    <item name='org.springframework.core.task.SimpleAsyncTaskExecutor org.springframework.util.concurrent.ListenableFuture&lt;T&gt; submitListenable(java.util.concurrent.Callable&lt;T&gt;)'>
        <annotation name='org.jetbrains.annotations.NotNull'/>
    </item>
    <item name='org.springframework.core.task.SimpleAsyncTaskExecutor java.util.concurrent.Future&lt;?&gt; submit(java.lang.Runnable)'>
        <annotation name='org.jetbrains.annotations.NotNull'/>
    </item>
    <item name='org.springframework.core.task.SyncTaskExecutor void execute(java.lang.Runnable) 0'>
        <annotation name='org.jetbrains.annotations.NotNull'/>
    </item>
    <item name='org.springframework.core.task.SimpleAsyncTaskExecutor void execute(java.lang.Runnable, long) 0'>
        <annotation name='org.jetbrains.annotations.NotNull'/>
    </item>
    <item name='org.springframework.core.task.AsyncListenableTaskExecutor org.springframework.util.concurrent.ListenableFuture&lt;?&gt; submitListenable(java.lang.Runnable)'>
        <annotation name='org.jetbrains.annotations.NotNull'/>
        <annotation name='org.jetbrains.kannotator.runtime.annotations.Propagated'>
            <val name="value" val="{org.jetbrains.kannotator.controlFlow.builder.analysis.NullabilityKey.class}"/>
        </annotation>
    </item>
    <item name='org.springframework.core.task.AsyncListenableTaskExecutor org.springframework.util.concurrent.ListenableFuture&lt;T&gt; submitListenable(java.util.concurrent.Callable&lt;T&gt;)'>
        <annotation name='org.jetbrains.annotations.NotNull'/>
        <annotation name='org.jetbrains.kannotator.runtime.annotations.Propagated'>
            <val name="value" val="{org.jetbrains.kannotator.controlFlow.builder.analysis.NullabilityKey.class}"/>
        </annotation>
    </item>
    <item name='org.springframework.core.task.SimpleAsyncTaskExecutor org.springframework.util.concurrent.ListenableFuture&lt;?&gt; submitListenable(java.lang.Runnable)'>
        <annotation name='org.jetbrains.annotations.NotNull'/>
    </item>
    <item name='org.springframework.core.task.AsyncTaskExecutor java.util.concurrent.Future&lt;?&gt; submit(java.lang.Runnable)'>
        <annotation name='org.jetbrains.annotations.NotNull'/>
        <annotation name='org.jetbrains.kannotator.runtime.annotations.Propagated'>
            <val name="value" val="{org.jetbrains.kannotator.controlFlow.builder.analysis.NullabilityKey.class}"/>
        </annotation>
    </item>
    <item name='org.springframework.core.task.AsyncTaskExecutor void execute(java.lang.Runnable, long) 0'>
        <annotation name='org.jetbrains.annotations.NotNull'/>
        <annotation name='org.jetbrains.kannotator.runtime.annotations.Propagated'>
            <val name="value" val="{org.jetbrains.kannotator.controlFlow.builder.analysis.NullabilityKey.class}"/>
        </annotation>
    </item>
    <item name='org.springframework.core.task.TaskExecutor void execute(java.lang.Runnable) 0'>
        <annotation name='org.jetbrains.annotations.NotNull'/>
        <annotation name='org.jetbrains.kannotator.runtime.annotations.Propagated'>
            <val name="value" val="{org.jetbrains.kannotator.controlFlow.builder.analysis.NullabilityKey.class}"/>
        </annotation>
    </item>
    <item name='org.springframework.core.task.AsyncTaskExecutor java.util.concurrent.Future&lt;T&gt; submit(java.util.concurrent.Callable&lt;T&gt;)'>
        <annotation name='org.jetbrains.annotations.NotNull'/>
        <annotation name='org.jetbrains.kannotator.runtime.annotations.Propagated'>
            <val name="value" val="{org.jetbrains.kannotator.controlFlow.builder.analysis.NullabilityKey.class}"/>
        </annotation>
    </item>
    <item name='org.springframework.core.task.SimpleAsyncTaskExecutor void execute(java.lang.Runnable) 0'>
        <annotation name='org.jetbrains.annotations.NotNull'/>
    </item>
    <item name='org.springframework.core.task.SimpleAsyncTaskExecutor java.util.concurrent.Future&lt;T&gt; submit(java.util.concurrent.Callable&lt;T&gt;)'>
        <annotation name='org.jetbrains.annotations.NotNull'/>
    </item>
</root>
